{"cameraMode":{"drawMode":0,"name":"Shaded","section":"Shading Mode"},"sceneLighting":false,"audioPlay":false,"sceneViewState":{"m_AlwaysRefresh":false,"showFog":true,"showSkybox":false,"showFlares":true,"showImageEffects":true,"showParticleSystems":true,"showVisualEffectGraphs":true,"m_FxEnabled":true},"in2DMode":false,"pivot":{"x":-10.126871109008789,"y":10.805978775024414,"z":14.394763946533204},"rotation":{"x":-0.10935936123132706,"y":-0.813658595085144,"z":0.5475631952285767,"w":-0.1619618684053421},"size":3.5997135639190676,"orthographic":false}